flightpath/__init__.py
flightpath/cli.py
flightpath/config.py
flightpath/tracer.py
flightpath-0.2.2.dist-info/METADATA
flightpath-0.2.2.dist-info/WHEEL
flightpath-0.2.2.dist-info/entry_points.txt
flightpath-0.2.2.dist-info/licenses/LICENSE
flightpath-0.2.2.dist-info/RECORD
