Metadata-Version: 2.4
Name: flightpath
Version: 0.2.2
Summary: A command-line tool for analyzing critical paths in Apache Airflow DAGs.
Author-email: Andrew Hannigan <andrew.s.hannigan@gmail.com>
License-File: LICENSE
Requires-Python: >=3.9
Requires-Dist: apache-airflow-client>=2.10.0
Requires-Dist: click>=8.1.7
Requires-Dist: duckdb>=1.1.1
Requires-Dist: requests>=2.32.3
